riddhulib/__init__.py
riddhulib/addcode.py
riddhulib-0.1.2.dist-info/METADATA
riddhulib-0.1.2.dist-info/WHEEL
riddhulib-0.1.2.dist-info/top_level.txt
riddhulib-0.1.2.dist-info/RECORD
