Metadata-Version: 2.4
Name: riddhulib
Version: 0.1.2
Summary: A simple addition library by Riddhesh with comments and docstrings.
Author: Riddhesh Wagvekar
Requires-Python: >=3.6
Dynamic: author
Dynamic: requires-python
Dynamic: summary
